loading/__init__.py
loading/load_save.py
utils/__init__.py
utils/all_utils.py
PythonDemoPackage-0.0.6.dist-info/LICENSE
PythonDemoPackage-0.0.6.dist-info/METADATA
PythonDemoPackage-0.0.6.dist-info/WHEEL
PythonDemoPackage-0.0.6.dist-info/top_level.txt
PythonDemoPackage-0.0.6.dist-info/RECORD
