Metadata-Version: 2.1
Name: PythonDemoPackage
Version: 0.0.6
Summary: A small example package
Home-page: https://github.com/entbappy/PythonDemoPackage
Author: Bappy Ahmed
Author-email: entbappy73@gmail.com
License: UNKNOWN
Project-URL: Bug Tracker, https://github.com/entbappy/PythonDemoPackage/issues
Platform: UNKNOWN
Classifier: Programming Language :: Python :: 3
Classifier: License :: OSI Approved :: MIT License
Classifier: Operating System :: OS Independent
Requires-Python: >=3.7
License-File: LICENSE
Requires-Dist: pandas
Requires-Dist: PyYAML
